dask_flood_mapper/__init__.py
dask_flood_mapper/_version.py
dask_flood_mapper/app.py
dask_flood_mapper/calculation.py
dask_flood_mapper/catalog.py
dask_flood_mapper/cli.py
dask_flood_mapper/config.yaml
dask_flood_mapper/flood.py
dask_flood_mapper/processing.py
dask_flood_mapper/stac_config.py
dask_flood_mapper/templates/index.html
dask_flood_mapper-2025.4.17.dist-info/licenses/LICENSE.txt
dask_flood_mapper-2025.4.17.dist-info/METADATA
dask_flood_mapper-2025.4.17.dist-info/WHEEL
dask_flood_mapper-2025.4.17.dist-info/entry_points.txt
dask_flood_mapper-2025.4.17.dist-info/top_level.txt
dask_flood_mapper-2025.4.17.dist-info/RECORD
