Metadata-Version: 2.4
Name: dask_flood_mapper
Version: 2025.4.17
Summary: Map floods with Sentinel-1 radar images. We replicate in this package the work
Author: Martin Schobben, Thais Beham
Author-email: martin.schobben@tuwien.ac.at
Platform: any
Classifier: Intended Audience :: Science/Research
Classifier: Topic :: Scientific/Engineering
Classifier: Topic :: Scientific/Engineering :: GIS
Classifier: Topic :: Software Development :: Libraries
Classifier: Programming Language :: Python :: 3
Classifier: Programming Language :: Python :: 3.10
Classifier: Operating System :: POSIX
Classifier: Natural Language :: English
License-File: LICENSE.txt
Requires-Dist: pystac_client>=0.8.6
Requires-Dist: odc-stac>=0.3.10
Requires-Dist: dask[distributed]<=2024.5.2
Requires-Dist: rioxarray>=0.17.0
Requires-Dist: appdirs
Provides-Extra: test
Requires-Dist: pytest; extra == "test"
Requires-Dist: pytest-cov; extra == "test"
Provides-Extra: remote
Requires-Dist: eodc>=2025.3.2; extra == "remote"
Requires-Dist: dask-gateway<2024.1.0,>=2023.8.0; extra == "remote"
Provides-Extra: docs
Requires-Dist: jupyter-book; extra == "docs"
Requires-Dist: jupyter_bokeh; extra == "docs"
Requires-Dist: hvplot; extra == "docs"
Requires-Dist: geoviews; extra == "docs"
Requires-Dist: datashader; extra == "docs"
Requires-Dist: rich; extra == "docs"
Provides-Extra: dev
Requires-Dist: ruff; extra == "dev"
Requires-Dist: nbstripout; extra == "dev"
Requires-Dist: pre-commit; extra == "dev"
Provides-Extra: app
Requires-Dist: flask; extra == "app"
Requires-Dist: flask_cors; extra == "app"
Requires-Dist: panel; extra == "app"
Requires-Dist: hvplot; extra == "app"
Requires-Dist: geoviews; extra == "app"
Requires-Dist: datashader; extra == "app"
Provides-Extra: all
Requires-Dist: pytest; extra == "all"
Requires-Dist: pytest-cov; extra == "all"
Requires-Dist: eodc>=2025.3.2; extra == "all"
Requires-Dist: dask-gateway<2024.1.0,>=2023.8.0; extra == "all"
Requires-Dist: jupyter-book; extra == "all"
Requires-Dist: jupyter_bokeh; extra == "all"
Requires-Dist: hvplot; extra == "all"
Requires-Dist: geoviews; extra == "all"
Requires-Dist: datashader; extra == "all"
Requires-Dist: rich; extra == "all"
Requires-Dist: ruff; extra == "all"
Requires-Dist: nbstripout; extra == "all"
Requires-Dist: pre-commit; extra == "all"
Requires-Dist: flask; extra == "all"
Requires-Dist: flask_cors; extra == "all"
Requires-Dist: panel; extra == "all"
Requires-Dist: hvplot; extra == "all"
Requires-Dist: geoviews; extra == "all"
Requires-Dist: datashader; extra == "all"
Dynamic: license-file
